Rss_Feed_data/Logging_skelton.py
Rss_Feed_data/Rss.py
Rss_Feed_data/__init__.py
Rss_Feed_data/__main__.py
Rss_Feed_data-0.1.1.dist-info/METADATA
Rss_Feed_data-0.1.1.dist-info/WHEEL
Rss_Feed_data-0.1.1.dist-info/top_level.txt
Rss_Feed_data-0.1.1.dist-info/RECORD
