Metadata-Version: 2.1
Name: Rss-Feed-data
Version: 0.1.1
Summary: Fech data from rss feed urls
Home-page: UNKNOWN
Author: Ramkiran
Author-email: UNKNOWN
License: MIT
Platform: UNKNOWN
Classifier: Programming Language :: Python :: 3.6
